harbis/__init__.py
harbis/__version__.py
harbis/harbis.py
harbis/upgrade.py
harbis-2017.0.1.1507220396.dist-info/DESCRIPTION.rst
harbis-2017.0.1.1507220396.dist-info/METADATA
harbis-2017.0.1.1507220396.dist-info/RECORD
harbis-2017.0.1.1507220396.dist-info/WHEEL
harbis-2017.0.1.1507220396.dist-info/entry_points.txt
harbis-2017.0.1.1507220396.dist-info/metadata.json
harbis-2017.0.1.1507220396.dist-info/top_level.txt
