Metadata-Version: 2.0
Name: harbis
Version: 2017.0.1.1507220396
Summary: Harbor Research Laboratory Assistant CLI
Home-page: https://gitlab.com/hrl-upm-es/harbis
Author: Harbor Research Laboratory UPM
Author-email: development@hrl-upm.es
License: MIT
Platform: UNKNOWN
Classifier: License :: OSI Approved :: MIT License
Classifier: Programming Language :: Python
Classifier: Programming Language :: Python :: 3.6
Classifier: Programming Language :: Python :: Implementation :: CPython
Classifier: Programming Language :: Python :: Implementation :: PyPy
Requires-Dist: requests
Requires-Dist: twine
Requires-Dist: Click
